[
  {"name": "Witch", "text": "Ugh . . ."},
  {"name": "Witch", "text": "Ah! Dear crow, you're back."},
  {"name": "Witch", "text": "*Cough* *Cough*"},
  {"name": "Witch", "text": "I see you've dealt with the dark sapling."},
  {"name": "Witch", "text": "I'm sure you have . . . questions."},
  {"name": "Witch", "text": "I am sorry, my d-"},
  {"name": "Witch", "text": "*COUGH* *COUGH*"},
  {"name": "Witch", "text": "Ugh I have sustained some deep wounds"},
  {"name": "Witch", "text": "I will go . . . lie down . . . for a bit"},
  {"name": "Witch", "text": "Be a dear and make me a healing potion"}
]
